{
    "code": 200,
    "msg": "success",
    "data": [
        {
            "name": "tag1",
            "title": "分类",
            "all": "不限",
            "con": [
                {
                    "id": 0,
                    "name": "不限"
                },
                {
                    "id": 1,
                    "name": "影楼"
                },
                {
                    "id": 2,
                    "name": "工作室"
                },
                {
                    "id": 3,
                    "name": "独立摄影师"
                }
            ],
            "selected": 0
        },
        {
            "name": "tag2",
            "title": "主打特色",
            "all": "不限",
            "con": [
                {
                    "id": 0,
                    "name": "不限"
                },
                {
                    "id": 1,
                    "name": "韩式"
                },
                {
                    "id": 2,
                    "name": "花海"
                },
                {
                    "id": 3,
                    "name": "欧美"
                },
                {
                    "id": 4,
                    "name": "个性"
                },
                {
                    "id": 5,
                    "name": "中国风"
                }
            ],
            "selected": 0
        },
        {
            "name": "tag3",
            "title": "区域",
            "all": "不限",
            "con": [
                {
                    "id": 0,
                    "name": "不限"
                },
                {
                    "id": "1",
                    "name": "郑东新区"
                },
                {
                    "id": "2",
                    "name": "惠济区"
                },
                {
                    "id": "3",
                    "name": "上街区"
                },
                {
                    "id": "4",
                    "name": "二七区"
                },
                {
                    "id": "5",
                    "name": "管城区"
                },
                {
                    "id": "6",
                    "name": "中原区"
                },
                {
                    "id": "7",
                    "name": "金水区"
                },
                {
                    "id": "8",
                    "name": "高新区"
                }
            ],
            "selected": 0
        }
    ]
}